qwiic_buzzer.py
sparkfun_qwiic_buzzer-0.1.6.dist-info/LICENSE
sparkfun_qwiic_buzzer-0.1.6.dist-info/METADATA
sparkfun_qwiic_buzzer-0.1.6.dist-info/WHEEL
sparkfun_qwiic_buzzer-0.1.6.dist-info/top_level.txt
sparkfun_qwiic_buzzer-0.1.6.dist-info/RECORD
