Metadata-Version: 2.1
Name: sparkfun_qwiic_buzzer
Version: 0.1.6
Summary: SparkFun Electronics Qwiic Buzzer
Home-page: https://www.sparkfun.com/products/24474
Author: SparkFun Electronics
Author-email: info@sparkfun.com
License: MIT
Keywords: electronics,maker
Classifier: Development Status :: 5 - Production/Stable
Classifier: Intended Audience :: Developers
Classifier: Topic :: Software Development :: Build Tools
Classifier: License :: OSI Approved :: MIT License
Classifier: Programming Language :: Python :: 3.11
Classifier: Programming Language :: Python :: 3.12
License-File: LICENSE
Requires-Dist: sparkfun-qwiic-i2c
